[
  {
    "comment": "Laval City Council",
    "area_id": "Q141810",
    "executive_item_id": "Q16251180",
    "positions": [
      {
        "comment": "Mayor of Laval",
        "position_item_id": "Q56097740"
      }
    ]
  },
  {
    "comment": "Vaughan City Council",
    "area_id": "Q44013",
    "executive_item_id": "Q17029808",
    "positions": [
      {
        "comment": "Mayor of Vaughan",
        "position_item_id": "Q56099574"
      }
    ]
  },
  {
    "comment": "Halifax Regional Council",
    "area_id": "Q2141",
    "executive_item_id": "Q17107607",
    "positions": [
      {
        "comment": "Mayor of Halifax",
        "position_item_id": "Q18693083"
      }
    ]
  },
  {
    "comment": "Legislature of Yukon",
    "area_id": "Q2009",
    "executive_item_id": "Q17108558",
    "positions": [
      {
        "comment": "Premier of Yukon",
        "position_item_id": "Q12270260"
      }
    ]
  },
  {
    "comment": "Government of Manitoba",
    "area_id": "Q1948",
    "executive_item_id": "Q20552083",
    "positions": [
      {
        "comment": "Premier of Manitoba",
        "position_item_id": "Q3401758"
      }
    ]
  },
  {
    "comment": "Toronto City Council",
    "area_id": "Q172",
    "executive_item_id": "Q2444341",
    "positions": [
      {
        "comment": "Mayor of Toronto",
        "position_item_id": "Q14927262"
      }
    ]
  },
  {
    "comment": "Cabinet of Canada",
    "area_id": "Q16",
    "executive_item_id": "Q2458227",
    "positions": [
      {
        "comment": "Prime Minister of Canada",
        "position_item_id": "Q839078"
      }
    ]
  },
  {
    "comment": "Executive Council of New Brunswick",
    "area_id": "Q1965",
    "executive_item_id": "Q2993946",
    "positions": [
      {
        "comment": "maire de Saint-Jean",
        "position_item_id": "Q28382706"
      }
    ]
  },
  {
    "comment": "Ottawa City Council",
    "area_id": "Q1930",
    "executive_item_id": "Q2994125",
    "positions": [
      {
        "comment": "Mayor of Ottawa",
        "position_item_id": "Q47488905"
      }
    ]
  },
  {
    "comment": "Gatineau City Council",
    "area_id": "Q141844",
    "executive_item_id": "Q2994126",
    "positions": [
      {
        "comment": "Mayor of Gatineau",
        "position_item_id": "Q56071331"
      }
    ]
  },
  {
    "comment": "Quebec City Council",
    "area_id": "Q2145",
    "executive_item_id": "Q2994129",
    "positions": [
      {
        "comment": "Mayor of Quebec City",
        "position_item_id": "Q47490293"
      }
    ]
  },
  {
    "comment": "Montreal City Council",
    "area_id": "Q340",
    "executive_item_id": "Q2994131",
    "positions": [
      {
        "comment": "Mayor of Montreal",
        "position_item_id": "Q177645"
      },
      {
        "comment": "Borough Mayor (Montreal)",
        "position_item_id": "Q47450833"
      }
    ]
  },
  {
    "comment": "Government of British Columbia",
    "area_id": "Q1974",
    "executive_item_id": "Q30295427",
    "positions": [
      {
        "comment": "Premier of British Columbia",
        "position_item_id": "Q7240349"
      }
    ]
  },
  {
    "comment": "Government of Saskatchewan",
    "area_id": "Q1989",
    "executive_item_id": "Q30295437",
    "positions": [
      {
        "comment": "Premier of Saskatchewan",
        "position_item_id": "Q6578215"
      }
    ]
  },
  {
    "comment": "Government of New Brunswick",
    "area_id": "Q1965",
    "executive_item_id": "Q3112626",
    "positions": [
      {
        "comment": "Premier of New Brunswick",
        "position_item_id": "Q12270252"
      }
    ]
  },
  {
    "comment": "Government of Quebec",
    "area_id": "Q176",
    "executive_item_id": "Q3112634",
    "positions": [
      {
        "comment": "Premier of Quebec",
        "position_item_id": "Q2911019"
      }
    ]
  },
  {
    "comment": "Government of Alberta",
    "area_id": "Q1951",
    "executive_item_id": "Q33121932",
    "positions": [
      {
        "comment": "Premier of Alberta",
        "position_item_id": "Q3401750"
      }
    ]
  },
  {
    "comment": "Government of Nunavut",
    "area_id": "Q2023",
    "executive_item_id": "Q33121937",
    "positions": [
      {
        "comment": "Premier of Nunavut",
        "position_item_id": "Q4377222"
      }
    ]
  },
  {
    "comment": "Calgary City Council",
    "area_id": "Q36312",
    "executive_item_id": "Q4145705",
    "positions": [
      {
        "comment": "Mayor of Calgary",
        "position_item_id": "Q47455744"
      }
    ]
  },
  {
    "comment": "Vancouver City Council",
    "area_id": "Q24639",
    "executive_item_id": "Q47489643",
    "positions": [
      {
        "comment": "Mayor of Vancouver",
        "position_item_id": "Q24255207"
      }
    ]
  },
  {
    "comment": "Winnipeg City Council",
    "area_id": "Q2135",
    "executive_item_id": "Q47489645",
    "positions": [
      {
        "comment": "Mayor of Winnipeg",
        "position_item_id": "Q47490035"
      }
    ]
  },
  {
    "comment": "Brampton City Council",
    "area_id": "Q44198",
    "executive_item_id": "Q4956221",
    "positions": [
      {
        "comment": "Mayor of Brampton",
        "position_item_id": "Q56043125"
      }
    ]
  },
  {
    "comment": "Edmonton City Council",
    "area_id": "Q2096",
    "executive_item_id": "Q5339025",
    "positions": [
      {
        "comment": "Mayor of Edmonton",
        "position_item_id": "Q21094906"
      }
    ]
  },
  {
    "comment": "Executive Council of the Northwest Territories",
    "area_id": "Q2007",
    "executive_item_id": "Q5419831",
    "positions": [
      {
        "comment": "Premier of the Northwest Territories",
        "position_item_id": "Q7240368"
      }
    ]
  },
  {
    "comment": "Government of Newfoundland and Labrador",
    "area_id": "Q2003",
    "executive_item_id": "Q5589273",
    "positions": [
      {
        "comment": "Premier of Newfoundland and Labrador",
        "position_item_id": "Q7240356"
      }
    ]
  },
  {
    "comment": "Government of Nova Scotia",
    "area_id": "Q1952",
    "executive_item_id": "Q5589276",
    "positions": [
      {
        "comment": "Premier of Nova Scotia",
        "position_item_id": "Q7240360"
      }
    ]
  },
  {
    "comment": "Government of Ontario",
    "area_id": "Q1904",
    "executive_item_id": "Q5589283",
    "positions": [
      {
        "comment": "Premier of Ontario",
        "position_item_id": "Q2560704"
      }
    ]
  },
  {
    "comment": "Government of Prince Edward Island",
    "area_id": "Q1979",
    "executive_item_id": "Q5589299",
    "positions": [
      {
        "comment": "Premier of Prince Edward Island",
        "position_item_id": "Q7240361"
      }
    ]
  },
  {
    "comment": "Hamilton, Ontario City Council",
    "area_id": "Q133116",
    "executive_item_id": "Q5644769",
    "positions": [
      {
        "comment": "mayor of Hamilton, Ontario",
        "position_item_id": "Q56071664"
      }
    ]
  },
  {
    "comment": "London City Council",
    "area_id": "Q92561",
    "executive_item_id": "Q6670238",
    "positions": [
      {
        "comment": "Mayor of London",
        "position_item_id": "Q56098876"
      }
    ]
  },
  {
    "comment": "Markham City Council",
    "area_id": "Q44016",
    "executive_item_id": "Q6770993",
    "positions": [
      {
        "comment": "Mayor of Markham",
        "position_item_id": "Q56099530"
      }
    ]
  },
  {
    "comment": "Mississauga City Council",
    "area_id": "Q50816",
    "executive_item_id": "Q6878950",
    "positions": [
      {
        "comment": "Mayor of Mississauga",
        "position_item_id": "Q56100961"
      }
    ]
  },
  {
    "comment": "Surrey City Council",
    "area_id": "Q390583",
    "executive_item_id": "Q7646781",
    "positions": [
      {
        "comment": "Mayor of Surrey",
        "position_item_id": "Q56099619"
      }
    ]
  }
]